flake8_pathlib/__init__.py
flake8_pathlib/checker.py
flake8_pathlib-0.1.3.dist-info/entry_points.txt
flake8_pathlib-0.1.3.dist-info/WHEEL
flake8_pathlib-0.1.3.dist-info/METADATA
flake8_pathlib-0.1.3.dist-info/RECORD
